[
  {
    "pk": 3490678,
    "translation": "CUNP",
    "book": 9,
    "chapter": 4,
    "verse": 1,
    "text": "<e>以色列</e>人出去與<e>非利士</e>人打仗，安營在<e>以便以謝</e>；<e>非利士</e>人安營在<e>亞弗</e>。",
    "comment": "<a href='/CUNP/9/5/1'>撒上 5:1</a> <u>非利士</u>人將神的<na>約</na>櫃從<u>以便以謝</u>抬到<u>亞實突</u>。<p><a href='/CUNP/9/7/12'>7:12</a> <u>撒母耳</u>將一塊石頭立在<u>米斯巴</u>和<u>善</u>的中間，給石頭起名叫<u>以便以謝</u>，說：「到如今耶和華都幫助我們。」"
  },
  {
    "pk": 3490679,
    "translation": "CUNP",
    "book": 9,
    "chapter": 4,
    "verse": 2,
    "text": "<e>非利士</e>人向<e>以色列</e>人擺陣。兩軍交戰的時候，<e>以色列</e>人敗在<e>非利士</e>人面前；<e>非利士</e>人在戰場上殺了他們的軍兵約有四千人。"
  },
  {
    "pk": 3490680,
    "translation": "CUNP",
    "book": 9,
    "chapter": 4,
    "verse": 3,
    "text": "百姓回到營裏，<e>以色列</e>的長老說：「耶和華今日為何使我們敗在<e>非利士</e>人面前呢？我們不如將耶和華的約櫃從<e>示羅</e>抬到我們這裏來，好在我們中間救我們脫離敵人的手。」"
  },
  {
    "pk": 3490681,
    "translation": "CUNP",
    "book": 9,
    "chapter": 4,
    "verse": 4,
    "text": "於是百姓打發人到<e>示羅</e>，從那裏將坐在二基路伯上萬軍之耶和華的約櫃抬來。<e>以利</e>的兩個兒子<e>何弗尼</e>、<e>非尼哈</e>與神的約櫃同來。",
    "comment": "<a href='/CUNP/2/25/18'>出 25:18</a>, <a href='/CUNP/2/25/22'>22</a> 要用金子錘出兩個基路伯來，安在施恩座的兩頭。……我要在那裏與你相會，又要從法櫃施恩座上二基路伯中間，和你說我所要吩咐你傳給<u>以色列</u>人的一切事。」<p><a href='/CUNP/4/7/89'>民 7:89</a> <u>摩西</u>進會幕要與耶和華說話的時候，聽見法櫃的施恩座以上、二基路伯中間有與他說話的聲音，就是耶和華與他說話。<br><a href='/CUNP/10/6/2'>撒下 6:2</a> <u>大衛</u>起身，率領跟隨他的眾人前往，要從<u>巴拉‧猶大</u>將神的<na>約</na>櫃運來；這<na>約</na>櫃就是坐在二基路伯上萬軍之耶和華留名的<na>約</na>櫃。<p><a href='/CUNP/19/80/1'>詩 80:1</a> 〔亞薩的詩，交與伶長。調用為證的百合花。〕領<u>約瑟</u>如領羊群之<u>以色列</u>的牧者啊，求你留心聽！坐在二基路伯上的啊，求你發出光來！<p><a href='/CUNP/19/99/1'>99:1</a> 耶和華作王；萬民當戰抖！他坐在二基路伯上，地當動搖。"
  },
  {
    "pk": 3490682,
    "translation": "CUNP",
    "book": 9,
    "chapter": 4,
    "verse": 5,
    "text": "耶和華的約櫃到了營中，<e>以色列</e>眾人就大聲歡呼，地便震動。"
  },
  {
    "pk": 3490683,
    "translation": "CUNP",
    "book": 9,
    "chapter": 4,
    "verse": 6,
    "text": "<e>非利士</e>人聽見歡呼的聲音，就說：「在<e>希伯來</e>人營裏大聲歡呼，是甚麼緣故呢？」隨後就知道耶和華的<i>約</i>櫃到了營中。"
  },
  {
    "pk": 3490684,
    "translation": "CUNP",
    "book": 9,
    "chapter": 4,
    "verse": 7,
    "text": "<e>非利士</e>人就懼怕起來，說：「有神到了他們營中」；又說：「我們有禍了！向來不曾有這樣的事。"
  },
  {
    "pk": 3490685,
    "translation": "CUNP",
    "book": 9,
    "chapter": 4,
    "verse": 8,
    "text": "我們有禍了！誰能救我們脫離這些大能之神的手呢？從前在曠野用各樣災殃擊打<e>埃及</e>人的，就是這些神。"
  },
  {
    "pk": 3490686,
    "translation": "CUNP",
    "book": 9,
    "chapter": 4,
    "verse": 9,
    "text": "<e>非利士</e>人哪，你們要剛強，要作大丈夫，免得作<e>希伯來</e>人的奴僕，如同他們作你們的奴僕一樣。你們要作大丈夫，與他們爭戰。」",
    "comment": "<a href='/CUNP/46/16/13'>林前 16:13</a> 你們務要警醒，在真道上站立得穩，要作大丈夫，要剛強。<br><a href='/CUNP/7/13/1'>士 13:1</a> <u>以色列</u>人又行耶和華眼中看為惡的事，耶和華將他們交在<u>非利士</u>人手中四十年。"
  },
  {
    "pk": 3490687,
    "translation": "CUNP",
    "book": 9,
    "chapter": 4,
    "verse": 10,
    "text": "<e>非利士</e>人和<e>以色列</e>人打仗，<e>以色列</e>人敗了，各向各家奔逃，被殺的人甚多，<e>以色列</e>的步兵仆倒了三萬。",
    "comment": "<a href='/CUNP/9/4/2'>撒上 4:2</a> <u>非利士</u>人向<u>以色列</u>人擺陣。兩軍交戰的時候，<u>以色列</u>人敗在<u>非利士</u>人面前；<u>非利士</u>人在戰場上殺了他們的軍兵約有四千人。<p><a href='/CUNP/3/26/17'>利 26:17</a> 我要向你們變臉，你們就要敗在仇敵面前。恨惡你們的，必轄管你們；無人追趕，你們卻要逃跑。<p><a href='/CUNP/5/28/25'>申 28:25</a>「耶和華必使你敗在仇敵面前，你從一條路去攻擊他們，必從七條路逃跑。你必在天下萬國中拋來拋去。<p><a href='/CUNP/19/78/9'>詩 78:9</a>, <a href='/CUNP/19/78/62'>62</a> <u>以法蓮</u>的子孫帶著兵器，拿著弓，臨陣之日轉身退後。……並將他的百姓交與刀劍，向他的產業發怒。"
  },
  {
    "pk": 3490688,
    "translation": "CUNP",
    "book": 9,
    "chapter": 4,
    "verse": 11,
    "text": "神的<i>約</i>櫃被擄去，<e>以利</e>的兩個兒子<e>何弗尼</e>、<e>非尼哈</e>也都被殺了。",
    "comment": "<a href='/CUNP/9/2/34'>撒上 2:34</a> 你的兩個兒子<u>何弗尼</u>、<u>非尼哈</u>所遭遇的事可作你的證據：他們二人必一日同死。<p><a href='/CUNP/19/78/64'>詩 78:64</a> 祭司倒在刀下，寡婦卻不哀哭。<br><a href='/CUNP/9/2/32'>撒上 2:32</a> 在<na>神</na>使<u>以色列</u>人享福的時候，你必看見我居所的敗落。在你家中必永遠沒有一個老年人。<p><a href='/CUNP/19/78/61'>詩 78:61</a> 又將他的約櫃<small>〔原文作「能力」〕</small>交與人擄去，將他的榮耀交在敵人手中；"
  },
  {
    "pk": 3490689,
    "translation": "CUNP",
    "book": 9,
    "chapter": 4,
    "verse": 12,
    "text": "當日，有一個<e>便雅憫</e>人從陣上逃跑，衣服撕裂，頭蒙灰塵，來到<e>示羅</e>。",
    "comment": "<a href='/CUNP/6/7/6'>書 7:6</a> <u>約書亞</u>便撕裂衣服；他和<u>以色列</u>的長老把灰撒在頭上，在耶和華的<na>約</na>櫃前俯伏在地，直到晚上。<p><a href='/CUNP/10/13/19'>撒下 13:19</a> <u>她瑪</u>把灰塵撒在頭上，撕裂所穿的彩衣，以手抱頭，一面行走，一面哭喊。<p><a href='/CUNP/10/15/32'>15:32</a> <u>大衛</u>到了<na>山</na>頂、敬拜神的地方，見<u>亞基</u>人<u>戶篩</u>，衣服撕裂，頭蒙灰塵來迎接他。<p><a href='/CUNP/16/9/1'>尼 9:1</a> 這月二十四日，<u>以色列</u>人聚集禁食，身穿麻衣，頭蒙灰塵。<p><a href='/CUNP/18/2/12'>伯 2:12</a> 他們遠遠地舉目觀看，認不出他來，就放聲大哭。各人撕裂外袍，把塵土向天揚起來，落在自己的頭上。<br><a href='/CUNP/10/1/2'>撒下 1:2</a> 第三天，有一人從<u>掃羅</u>的營裏出來，衣服撕裂，頭蒙灰塵，到<u>大衛</u>面前伏地叩拜。"
  },
  {
    "pk": 3490690,
    "translation": "CUNP",
    "book": 9,
    "chapter": 4,
    "verse": 13,
    "text": "到了的時候，<e>以利</e>正在道旁坐在自己的位上觀望，為神的<i>約</i>櫃心裏擔憂。那人進城報信，合城的人就都呼喊起來。",
    "comment": "<a href='/CUNP/9/1/9'>撒上 1:9</a> 他們在<u>示羅</u>吃喝完了，<u>哈拿</u>就站起來。祭司<u>以利</u>在耶和華殿的門框旁邊，坐在自己的位上。"
  },
  {
    "pk": 3490691,
    "translation": "CUNP",
    "book": 9,
    "chapter": 4,
    "verse": 14,
    "text": "<e>以利</e>聽見呼喊的聲音就問說：「這喧嚷是甚麼緣故呢？」那人急忙來報信給<e>以利</e>。"
  },
  {
    "pk": 3490692,
    "translation": "CUNP",
    "book": 9,
    "chapter": 4,
    "verse": 15,
    "text": "那時<e>以利</e>九十八歲了，眼目發直，不能看見。",
    "comment": "<a href='/CUNP/9/3/2'>撒上 3:2</a> 一日，<u>以利</u>睡臥在自己的地方；他眼目昏花，看不分明。"
  },
  {
    "pk": 3490693,
    "translation": "CUNP",
    "book": 9,
    "chapter": 4,
    "verse": 16,
    "text": "那人對<e>以利</e>說：「我是從陣上來的，今日我從陣上逃回。」<e>以利</e>說：「我兒，事情怎樣？」",
    "comment": "<a href='/CUNP/10/1/4'>撒下 1:4</a> <u>大衛</u>又問他說：「事情怎樣？請你告訴我。」他回答說：「百姓從陣上逃跑，也有許多人仆倒死亡；<u>掃羅</u>和他兒子<u>約拿單</u>也死了。」"
  },
  {
    "pk": 3490694,
    "translation": "CUNP",
    "book": 9,
    "chapter": 4,
    "verse": 17,
    "text": "報信的回答說：「<e>以色列</e>人在<e>非利士</e>人面前逃跑，民中被殺的甚多！你的兩個兒子<e>何弗尼</e>、<e>非尼哈</e>也都死了，並且神的<i>約</i>櫃被擄去。」"
  },
  {
    "pk": 3490695,
    "translation": "CUNP",
    "book": 9,
    "chapter": 4,
    "verse": 18,
    "text": "他一提神的<i>約</i>櫃，<e>以利</e>就從他的位上往後跌倒，在門旁折斷頸項而死；因為他年紀老邁，身體沉重。<e>以利</e>作<e>以色列</e>的士師四十年。"
  },
  {
    "pk": 3490696,
    "translation": "CUNP",
    "book": 9,
    "chapter": 4,
    "verse": 19,
    "text": "<e>以利</e>的兒婦、<e>非尼哈</e>的妻懷孕將到產期，她聽見神的<i>約</i>櫃被擄去，公公和丈夫都死了，就猛然疼痛，曲身生產；"
  },
  {
    "pk": 3490697,
    "translation": "CUNP",
    "book": 9,
    "chapter": 4,
    "verse": 20,
    "text": "將要死的時候，旁邊站著的婦人們對她說：「不要怕！你生了男孩子了。」她卻不回答，也不放在心上。",
    "comment": "<a href='/CUNP/1/35/17'>創 35:17</a> 正在艱難的時候，收生婆對她說：「不要怕，你又要得一個兒子了。」"
  },
  {
    "pk": 3490698,
    "translation": "CUNP",
    "book": 9,
    "chapter": 4,
    "verse": 21,
    "text": "她給孩子起名叫<e>以迦博</e>，說：「榮耀離開<e>以色列</e>了！」這是因神的<i>約</i>櫃被擄去，又因她公公和丈夫都死了。",
    "comment": "<a href='/CUNP/19/26/8'>詩 26:8</a> 耶和華啊，我喜愛你所住的殿和你顯榮耀的居所。<p><a href='/CUNP/19/78/61'>78:61</a> 又將他的約櫃<small>〔原文作「能力」〕</small>交與人擄去，將他的榮耀交在敵人手中；<br><a href='/CUNP/9/14/3'>撒上 14:3</a> 在那裏有<u>亞希突</u>的兒子<u>亞希亞</u>，穿著以弗得。（<u>亞希突</u>是<u>以迦博</u>的哥哥，<u>非尼哈</u>的兒子，<u>以利</u>的孫子。<u>以利</u>從前在<u>示羅</u>作耶和華的祭司。）<u>約拿單</u>去了，百姓卻不知道。"
  },
  {
    "pk": 3490699,
    "translation": "CUNP",
    "book": 9,
    "chapter": 4,
    "verse": 22,
    "text": "她又說：「榮耀離開<e>以色列</e>，因為神的約櫃被擄去了。」"
  }
]
