[
  {
    "pk": 3496657,
    "translation": "CUNP",
    "book": 18,
    "chapter": 18,
    "verse": 1,
    "text": "<e>書亞</e>人<e>比勒達</e>回答說：<br/>"
  },
  {
    "pk": 3496658,
    "translation": "CUNP",
    "book": 18,
    "chapter": 18,
    "verse": 2,
    "text": "你尋索言語要到幾時呢？你可以揣摩思想，然後我們就說話。<br/>"
  },
  {
    "pk": 3496659,
    "translation": "CUNP",
    "book": 18,
    "chapter": 18,
    "verse": 3,
    "text": "我們為何算為畜生，在你眼中看作污穢呢？<br/>",
    "comment": "<a href='/CUNP/19/73/22'>詩 73:22</a> 我這樣愚昧無知，在你面前如畜類一般。"
  },
  {
    "pk": 3496660,
    "translation": "CUNP",
    "book": 18,
    "chapter": 18,
    "verse": 4,
    "text": "你這惱怒將自己撕裂的，難道大地為你見棄、磐石挪開原處嗎？",
    "comment": "<a href='/CUNP/18/13/14'>伯 13:14</a> 我何必把我的肉掛在牙上，將我的命放在手中。"
  },
  {
    "pk": 3496661,
    "translation": "CUNP",
    "book": 18,
    "chapter": 18,
    "verse": 5,
    "text": "惡人的亮光必要熄滅；他的火焰必不照耀。<br/>",
    "comment": "<a href='/CUNP/20/13/9'>箴 13:9</a> 義人的光明亮；<small>〔「明亮」原文作「歡喜」〕</small>惡人的燈要熄滅。<p><a href='/CUNP/20/20/20'>20:20</a> 咒罵父母的，他的燈必滅，變為漆黑的黑暗。<p><a href='/CUNP/20/24/20'>24:20</a> 因為，惡人終不得善報；惡人的燈也必熄滅。"
  },
  {
    "pk": 3496662,
    "translation": "CUNP",
    "book": 18,
    "chapter": 18,
    "verse": 6,
    "text": "他帳棚中的亮光要變為黑暗；他以上的燈也必熄滅。<br/>",
    "comment": "<a href='/CUNP/18/21/17'>伯 21:17</a> 惡人的燈何嘗熄滅？患難何嘗臨到他們呢？神何嘗發怒，<na>向他們</na>分散災禍呢？<p><a href='/CUNP/19/18/28'>詩 18:28</a> 你必點著我的燈；耶和華──我的神必照明我的黑暗。"
  },
  {
    "pk": 3496663,
    "translation": "CUNP",
    "book": 18,
    "chapter": 18,
    "verse": 7,
    "text": "他堅強的腳步必見狹窄；自己的計謀必將他絆倒。<br/>",
    "comment": "<a href='/CUNP/18/5/13'>伯 5:13</a> 他叫有智慧的中了自己的詭計，使狡詐人的計謀速速滅亡。"
  },
  {
    "pk": 3496664,
    "translation": "CUNP",
    "book": 18,
    "chapter": 18,
    "verse": 8,
    "text": "因為他被自己的腳陷入網中，走在纏人的網羅上。<br/>",
    "comment": "<a href='/CUNP/18/22/10'>伯 22:10</a> 因此，有網羅環繞你，有恐懼忽然使你驚惶；<p><a href='/CUNP/19/9/15'>詩 9:15</a> 外邦人陷在自己所掘的坑中；他們的腳在自己暗設的網羅裏纏住了。<p><a href='/CUNP/19/35/8'>35:8</a> 願災禍忽然臨到他身上！願他暗設的網纏住自己！願他落在其中遭災禍！"
  },
  {
    "pk": 3496665,
    "translation": "CUNP",
    "book": 18,
    "chapter": 18,
    "verse": 9,
    "text": "圈套必抓住他的腳跟；機關必擒獲他。<br/>",
    "comment": "<a href='/CUNP/18/5/5'>伯 5:5</a> 他的莊稼有飢餓的人吃盡了，就是在荊棘裏的也搶去了；他的財寶有網羅張口吞滅了。"
  },
  {
    "pk": 3496666,
    "translation": "CUNP",
    "book": 18,
    "chapter": 18,
    "verse": 10,
    "text": "活扣為他藏在土內；羈絆為他藏在路上。<br/>"
  },
  {
    "pk": 3496667,
    "translation": "CUNP",
    "book": 18,
    "chapter": 18,
    "verse": 11,
    "text": "四面的驚嚇要使他害怕，並且追趕他的腳跟。<br/>",
    "comment": "<a href='/CUNP/18/15/21'>伯 15:21</a> 驚嚇的聲音常在他耳中；在平安時，搶奪的必臨到他那裏。<p><a href='/CUNP/18/20/25'>20:25</a> 他把箭一抽，就從他身上出來；發光的箭頭從他膽中出來，有驚惶臨在他身上。<p><a href='/CUNP/24/6/25'>耶 6:25</a> 你們不要往田野去，也不要行在路上，因四圍有仇敵的刀劍和驚嚇。<p><a href='/CUNP/24/20/3'>20:3</a> 次日，<u>巴施戶珥</u>將<u>耶利米</u>開枷釋放。於是<u>耶利米</u>對他說：「耶和華不是叫你的名為<u>巴施戶珥</u>，乃是叫你<u>瑪歌珥‧米撒畢</u><small>〔就是「四面驚嚇」的意思〕</small>，<p><a href='/CUNP/24/46/5'>46:5</a> 我為何看見他們驚惶轉身退後呢？他們的勇士打敗了，急忙逃跑，並不回頭；驚嚇四圍都有！這是耶和華說的。<p><a href='/CUNP/24/49/29'>49:29</a> 他們的帳棚和羊群都要奪去，將幔子和一切器皿，並駱駝為自己掠去。人向他們喊著說：四圍都有驚嚇。"
  },
  {
    "pk": 3496668,
    "translation": "CUNP",
    "book": 18,
    "chapter": 18,
    "verse": 12,
    "text": "他的力量必因飢餓衰敗；禍患要在他旁邊等候。<br/>",
    "comment": "<a href='/CUNP/18/15/23'>伯 15:23</a> 他漂流在外求食，<na>說</na>：哪裏有食物呢？他知道黑暗的日子在他手邊預備好了。"
  },
  {
    "pk": 3496669,
    "translation": "CUNP",
    "book": 18,
    "chapter": 18,
    "verse": 13,
    "text": "他本身的肢體要被吞吃；死亡的長子要吞吃他的肢體。<br/>"
  },
  {
    "pk": 3496670,
    "translation": "CUNP",
    "book": 18,
    "chapter": 18,
    "verse": 14,
    "text": "他要從所倚靠的帳棚被拔出來，帶到驚嚇的王那裏。<br/>",
    "comment": "<a href='/CUNP/18/8/14'>伯 8:14</a> 他所仰賴的必折斷；他所倚靠的是蜘蛛網。<p><a href='/CUNP/18/11/20'>11:20</a> 但惡人的眼目必要失明。他們無路可逃；他們的指望就是氣絕。<p><a href='/CUNP/19/112/10'>詩 112:10</a> 惡人看見便惱恨，必咬牙而消化；惡人的心願要歸滅絕。<p><a href='/CUNP/20/10/28'>箴 10:28</a> 義人的盼望<na>必得</na>喜樂；惡人的指望必致滅沒。"
  },
  {
    "pk": 3496671,
    "translation": "CUNP",
    "book": 18,
    "chapter": 18,
    "verse": 15,
    "text": "不屬他的必住在他的帳棚裏；硫磺必撒在他所住之處。<br/>"
  },
  {
    "pk": 3496672,
    "translation": "CUNP",
    "book": 18,
    "chapter": 18,
    "verse": 16,
    "text": "下邊，他的根本要枯乾；上邊，他的枝子要剪除。<br/>",
    "comment": "<a href='/CUNP/18/29/19'>伯 29:19</a> 我的根長到水邊；露水終夜霑在我的枝上。<p><a href='/CUNP/23/5/24'>賽 5:24</a> 火苗怎樣吞滅碎秸，乾草怎樣落在火焰之中，照樣，他們的根必像朽<na>物</na>，他們的花必像灰塵飛騰；因為他們厭棄萬軍之耶和華的訓誨，藐視<u>以色列</u>聖者的言語。<p><a href='/CUNP/30/2/9'>摩 2:9</a> 我從<u>以色列</u>人面前除滅<u>亞摩利</u>人。他雖高大如香柏樹，堅固如橡樹，我卻上滅他的果子，下絕他的根本。<p><a href='/CUNP/39/4/1'>瑪 4:1</a> 萬軍之耶和華說：「那日臨近，勢如燒著的火爐，凡狂傲的和行惡的必如碎秸，在那日必被燒盡，根本枝條一無存留。"
  },
  {
    "pk": 3496673,
    "translation": "CUNP",
    "book": 18,
    "chapter": 18,
    "verse": 17,
    "text": "他的記念在地上必然滅亡；他的名字在街上也不存留。<br/>",
    "comment": "<a href='/CUNP/19/34/16'>詩 34:16</a> 耶和華向行惡的人變臉，要從世上除滅他們的名號。<p><a href='/CUNP/19/109/13'>109:13</a> 願他的後人斷絕，名字被塗抹，不傳於下代！<p><a href='/CUNP/20/2/22'>箴 2:22</a> 惟有惡人必然剪除；奸詐的，必然拔出。<p><a href='/CUNP/20/10/7'>10:7</a> 義人的紀念被稱讚；惡人的名字必朽爛。"
  },
  {
    "pk": 3496674,
    "translation": "CUNP",
    "book": 18,
    "chapter": 18,
    "verse": 18,
    "text": "他必從光明中被攆到黑暗裏，必被趕出世界。<br/>"
  },
  {
    "pk": 3496675,
    "translation": "CUNP",
    "book": 18,
    "chapter": 18,
    "verse": 19,
    "text": "在本民中必無子無孫；在寄居之地也無一人存留。<br/>",
    "comment": "<a href='/CUNP/23/14/22'>賽 14:22</a> 萬軍之耶和華說：我必興起攻擊他們，將<u>巴比倫</u>的名號和所餘剩的人，連子帶孫一併剪除。這是耶和華說的。<p><a href='/CUNP/24/22/30'>耶 22:30</a> 耶和華如此說：要寫明這人算為無子，是平生不得亨通的；因為他後裔中再無一人得亨通，能坐在<u>大衛</u>的寶座上治理<u>猶大</u>。"
  },
  {
    "pk": 3496676,
    "translation": "CUNP",
    "book": 18,
    "chapter": 18,
    "verse": 20,
    "text": "以後來的要驚奇他的日子，好像以前去的受了驚駭。<br/>",
    "comment": "<a href='/CUNP/19/37/13'>詩 37:13</a> 主要笑他，因見他<na>受罰</na>的日子將要來到。"
  },
  {
    "pk": 3496677,
    "translation": "CUNP",
    "book": 18,
    "chapter": 18,
    "verse": 21,
    "text": "不義之人的住處總是這樣；此乃不認識神之人的地步。",
    "comment": "<a href='/CUNP/24/9/3'>耶 9:3</a> 他們彎起舌頭像弓一樣，為要說謊話。他們在國中增長勢力，不是為行誠實，乃是惡上加惡，並不認識我。這是耶和華說的。<p><a href='/CUNP/24/10/25'>10:25</a> 願你將忿怒傾在不認識你的列國中，和不求告你名的各族上；因為他們吞了<u>雅各</u>，不但吞了，而且滅絕，把他的住處變為荒場。<p><a href='/CUNP/52/4/5'>帖前 4:5</a> 不放縱私慾的邪情，像那不認識神的外邦人。<p><a href='/CUNP/53/1/8'>帖後 1:8</a> 要報應那不認識神和那不聽從我主耶穌福音的人。<p><a href='/CUNP/56/1/16'>多 1:16</a> 他們說是認識神，行事卻和他相背；本是可憎惡的，是悖逆的，在各樣善事上是可廢棄的。"
  }
]
