[
  {
    "pk": 3488906,
    "translation": "CUNP",
    "book": 5,
    "chapter": 24,
    "verse": 1,
    "text": "「人若娶妻以後，見她有甚麼不合理的事，不喜悅她，就可以寫休書交在她手中，打發她離開夫家。",
    "comment": "<a href='/CUNP/40/5/31'>太 5:31</a>「又有話說：『人若休妻，就當給她休書。』<p><a href='/CUNP/40/19/7'>19:7</a> 法利賽人說：「這樣，<u>摩西</u>為甚麼吩咐給妻子休書，就可以休她呢？」<p><a href='/CUNP/41/10/4'>可 10:4</a> 他們說：「<u>摩西</u>許人寫了休書便可以休妻。」"
  },
  {
    "pk": 3488907,
    "translation": "CUNP",
    "book": 5,
    "chapter": 24,
    "verse": 2,
    "text": "婦人離開夫家以後，可以去嫁別人。"
  },
  {
    "pk": 3488908,
    "translation": "CUNP",
    "book": 5,
    "chapter": 24,
    "verse": 3,
    "text": "後夫若恨惡她，寫休書交在她手中，打發她離開夫家，或是娶她為妻的後夫死了，"
  },
  {
    "pk": 3488909,
    "translation": "CUNP",
    "book": 5,
    "chapter": 24,
    "verse": 4,
    "text": "打發她去的前夫不可在婦人玷污之後再娶她為妻，因為這是耶和華所憎惡的；不可使耶和華──你神所賜為業之地被玷污了。」",
    "comment": "<a href='/CUNP/24/3/1'>耶 3:1</a> 有話說：人若休妻，妻離他而去，作了別人的妻，前夫豈能再收回她來？<na>若收回她來</na>，那地豈不是大大玷污了嗎？但你和許多親愛的行邪淫，還可以歸向我。這是耶和華說的。"
  },
  {
    "pk": 3488910,
    "translation": "CUNP",
    "book": 5,
    "chapter": 24,
    "verse": 5,
    "text": "「新娶妻之人不可從軍出征，也不可託他辦理甚麼公事，可以在家清閒一年，使他所娶的妻快活。",
    "comment": "<a href='/CUNP/20/5/18'>箴 5:18</a> 要使你的泉源蒙福；要喜悅你幼年所娶的妻。<br><a href='/CUNP/5/20/7'>申 20:7</a> 誰聘定了妻，尚未迎娶，他可以回家去，恐怕他陣亡，別人去娶。』"
  },
  {
    "pk": 3488911,
    "translation": "CUNP",
    "book": 5,
    "chapter": 24,
    "verse": 6,
    "text": "「不可拿人的<i>全</i>盤磨石或是上磨石作當頭，因為這是拿<i>人的</i>命作當頭。"
  },
  {
    "pk": 3488912,
    "translation": "CUNP",
    "book": 5,
    "chapter": 24,
    "verse": 7,
    "text": "「若遇見人拐帶<e>以色列</e>中的一個弟兄，當奴才待他，或是賣了他，那拐帶人的就必治死。這樣，便將那惡從你們中間除掉。",
    "comment": "<a href='/CUNP/2/21/16'>出 21:16</a>「拐帶人口，或是把人賣了，或是留在他手下，必要把他治死。<br><a href='/CUNP/5/19/19'>申 19:19</a> 你們就要待他如同他想要待的弟兄。這樣，就把那惡從你們中間除掉。"
  },
  {
    "pk": 3488913,
    "translation": "CUNP",
    "book": 5,
    "chapter": 24,
    "verse": 8,
    "text": "「在大痲瘋的災病上，你們要謹慎，照祭司<e>利未</e>人一切所指教你們的留意遵行。我怎樣吩咐他們，你們要怎樣遵行。",
    "comment": "<a href='/CUNP/3/13/2'>利 13:2</a>「人的肉皮上若長了癤子，或長了癬，或長了火斑，在他肉皮上成了大痲瘋的災病，就要將他帶到祭司<u>亞倫</u>或<u>亞倫</u>作祭司的一個子孫面前。<p><a href='/CUNP/3/14/2'>14:2</a> 長大痲瘋得潔淨的日子，其例乃是這樣：要帶他去見祭司；"
  },
  {
    "pk": 3488914,
    "translation": "CUNP",
    "book": 5,
    "chapter": 24,
    "verse": 9,
    "text": "當記念出<e>埃及</e>後，在路上，耶和華──你神向<e>米利暗</e>所行的事。",
    "comment": "參看 <a href='/CUNP/42/17/32'>路 17:32</a> 你們要回想<u>羅得</u>的妻子。<p><a href='/CUNP/46/10/6'>林前 10:6</a> 這些事都是我們的鑑戒，叫我們不要貪戀惡事，像他們那樣貪戀的；<br><a href='/CUNP/4/12/10'>民 12:10</a> 雲彩從<na>會</na>幕上挪開了，不料，<u>米利暗</u>長了大痲瘋，有雪<na>那樣</na>白。<u>亞倫</u>一看<u>米利暗</u>長了大痲瘋，"
  },
  {
    "pk": 3488915,
    "translation": "CUNP",
    "book": 5,
    "chapter": 24,
    "verse": 10,
    "text": "「你借給鄰舍，不拘是甚麼，不可進他家拿他的當頭。"
  },
  {
    "pk": 3488916,
    "translation": "CUNP",
    "book": 5,
    "chapter": 24,
    "verse": 11,
    "text": "要站在外面，等那向你借貸的人把當頭拿出來交給你。"
  },
  {
    "pk": 3488917,
    "translation": "CUNP",
    "book": 5,
    "chapter": 24,
    "verse": 12,
    "text": "他若是窮人，你不可留他的當頭過夜。"
  },
  {
    "pk": 3488918,
    "translation": "CUNP",
    "book": 5,
    "chapter": 24,
    "verse": 13,
    "text": "日落的時候，總要把當頭還他，使他用那件衣服蓋著睡覺，他就為你祝福；這在耶和華──你神面前就是你的義了。",
    "comment": "<a href='/CUNP/2/22/26'>出 22:26</a> 你即或拿鄰舍的衣服作當頭，必在日落以先歸還他；<br><a href='/CUNP/18/29/11'>伯 29:11</a>, <a href='/CUNP/18/29/13'>13</a> 耳朵聽我的，就稱我有福；眼睛看我的，便稱讚我；……將要滅亡的為我祝福；我也使寡婦心中歡樂。<p><a href='/CUNP/18/31/20'>31:20</a> 我若不使他因我羊的毛得暖，為我祝福；<p><a href='/CUNP/47/9/13'>林後 9:13</a> 他們從這供給的事上得了憑據，知道你們承認基督順服他的福音，多多地捐錢給他們和眾人，便將榮耀歸與神。<p><a href='/CUNP/55/1/18'>提後 1:18</a> 願主使他在那日得主的憐憫。他在<u>以弗所</u>怎樣多多地服事我，是你明明知道的。<br><a href='/CUNP/5/6/25'>申 6:25</a> 我們若照耶和華──我們神所吩咐的一切誡命謹守遵行，這就是我們的義了。』」<p><a href='/CUNP/19/106/31'>詩 106:31</a> 那就算為他的義，世世代代，直到永遠。<p><a href='/CUNP/19/112/9'>112:9</a> 他施捨<na>錢財</na>，賙濟貧窮；他的仁義存到永遠。他的角必被高舉，大有榮耀。<p><a href='/CUNP/27/4/27'>但 4:27</a> 王啊，求你悅納我的諫言，以施行公義斷絕罪過，以憐憫窮人除掉罪孽，或者你的平安可以延長。」"
  },
  {
    "pk": 3488919,
    "translation": "CUNP",
    "book": 5,
    "chapter": 24,
    "verse": 14,
    "text": "「困苦窮乏的雇工，無論是你的弟兄或是在你城裏寄居的，你不可欺負他。",
    "comment": "<a href='/CUNP/39/3/5'>瑪 3:5</a> 萬軍之耶和華說：「我必臨近你們，施行審判。我必速速作見證，警戒行邪術的、犯姦淫的、起假誓的、虧負人之工價的、欺壓寡婦孤兒的、屈枉寄居的，和不敬畏我的。」"
  },
  {
    "pk": 3488920,
    "translation": "CUNP",
    "book": 5,
    "chapter": 24,
    "verse": 15,
    "text": "要當日給他工價，不可等到日落──因為他窮苦，把心放在工價上──恐怕他因你求告耶和華，罪便歸你了。",
    "comment": "<a href='/CUNP/3/19/13'>利 19:13</a>「不可欺壓你的鄰舍，也不可搶奪他的物。雇工人的工價，不可在你那裏過夜，留到早晨。<p><a href='/CUNP/24/22/13'>耶 22:13</a> 那行不義蓋房、行不公造樓、白白使用人的手工不給工價的有禍了！<p><a href='/CUNP/59/5/4'>雅 5:4</a> 工人給你們收割莊稼，你們虧欠他們的工錢，這工錢有聲音呼叫，並且那收割之人的冤聲已經入了萬軍之主的耳了。<br><a href='/CUNP/59/5/4'>雅 5:4</a> 工人給你們收割莊稼，你們虧欠他們的工錢，這工錢有聲音呼叫，並且那收割之人的冤聲已經入了萬軍之主的耳了。"
  },
  {
    "pk": 3488921,
    "translation": "CUNP",
    "book": 5,
    "chapter": 24,
    "verse": 16,
    "text": "「不可因子殺父，也不可因父殺子；凡被殺的都為本身的罪。",
    "comment": "<a href='/CUNP/12/14/6'>王下 14:6</a> 卻沒有治死殺王之人的兒子，是照<u>摩西</u>律法書上耶和華所吩咐的說：「不可因子殺父，也不可因父殺子，各人要為本身的罪而死。」<p><a href='/CUNP/14/25/4'>代下 25:4</a> 卻沒有治死他們的兒子，是照<u>摩西</u>律法書上耶和華所吩咐的說：「不可因子殺父，也不可因父殺子，各人要為本身的罪而死。」<p><a href='/CUNP/24/31/29-30'>耶 31:29-30</a> 當那些日子，人不再說：父親吃了酸葡萄，兒子的牙酸倒了。但各人必因自己的罪死亡；凡吃酸葡萄的，自己的牙必酸倒。」<p><a href='/CUNP/26/18/20'>結 18:20</a> 惟有犯罪的，他必死亡。兒子必不擔當父親的罪孽，父親也不擔當兒子的罪孽。義人的善果必歸自己，惡人的惡報也必歸自己。"
  },
  {
    "pk": 3488922,
    "translation": "CUNP",
    "book": 5,
    "chapter": 24,
    "verse": 17,
    "text": "「你不可向寄居的和孤兒屈枉正直，也不可拿寡婦的衣裳作當頭。",
    "comment": "<a href='/CUNP/2/22/21-22'>出 22:21-22</a>「不可虧負寄居的，也不可欺壓他，因為你們在<u>埃及</u>地也作過寄居的。不可苦待寡婦和孤兒；<p><a href='/CUNP/20/22/22'>箴 22:22</a> 貧窮人，你不可因他貧窮就搶奪他的物，也不可在城門口欺壓困苦人；<p><a href='/CUNP/23/1/23'>賽 1:23</a> 你的官長居心悖逆，與盜賊作伴，各都喜愛賄賂，追求贓私。他們不為孤兒伸冤；寡婦的案件也不得呈到他們面前。<p><a href='/CUNP/24/5/28'>耶 5:28</a> 他們肥胖光潤，作惡過甚，不為人伸冤！就是不為孤兒伸冤，不使他亨通，也不為窮人辨屈。<p><a href='/CUNP/24/22/3'>22:3</a> 耶和華如此說：你們要施行公平和公義，拯救被搶奪的脫離欺壓人的手，不可虧負寄居的和孤兒寡婦，不可以強暴待他們，在這地方也不可流無辜人的血。<p><a href='/CUNP/26/22/29'>結 22:29</a> 國內眾民一味地欺壓，慣行搶奪，虧負困苦窮乏的，背理欺壓寄居的。<p><a href='/CUNP/38/7/10'>亞 7:10</a> 不可欺壓寡婦、孤兒、寄居的，和貧窮人。誰都不可心裏謀害弟兄。』」<p><a href='/CUNP/39/3/5'>瑪 3:5</a> 萬軍之耶和華說：「我必臨近你們，施行審判。我必速速作見證，警戒行邪術的、犯姦淫的、起假誓的、虧負人之工價的、欺壓寡婦孤兒的、屈枉寄居的，和不敬畏我的。」<br><a href='/CUNP/2/22/26'>出 22:26</a> 你即或拿鄰舍的衣服作當頭，必在日落以先歸還他；"
  },
  {
    "pk": 3488923,
    "translation": "CUNP",
    "book": 5,
    "chapter": 24,
    "verse": 18,
    "text": "要記念你在<e>埃及</e>作過奴僕。耶和華──你的神從那裏將你救贖，所以我吩咐你這樣行。",
    "comment": "<a href='/CUNP/5/16/12'>申 16:12</a> 你也要記念你在<u>埃及</u>作過奴僕。你要謹守遵行這些律例。」<p><a href='/CUNP/5/24/22'>24:22</a> 你也要記念你在<u>埃及</u>地作過奴僕，所以我吩咐你這樣行。"
  },
  {
    "pk": 3488924,
    "translation": "CUNP",
    "book": 5,
    "chapter": 24,
    "verse": 19,
    "text": "「你在田間收割莊稼，若忘下一捆，不可回去再取，要留給寄居的與孤兒寡婦。這樣，耶和華──你神必在你手裏所辦的一切事上賜福與你。",
    "comment": "<a href='/CUNP/3/19/9-10'>利 19:9-10</a>「在你們的地收割莊稼，不可割盡田角，也不可拾取所遺落的。不可摘盡葡萄園的果子，也不可拾取葡萄園所掉的果子；要留給窮人和寄居的。我是耶和華──你們的神。<p><a href='/CUNP/3/23/22'>23:22</a>「在你們的地收割莊稼，不可割盡田角，也不可拾取所遺落的；要留給窮人和寄居的。我是耶和華──你們的神。」<br><a href='/CUNP/5/15/10'>申 15:10</a> 你總要給他，給他的時候心裏不可愁煩；因耶和華──你的神必在你這一切所行的，並你手裏所辦的事上，賜福與你。<p><a href='/CUNP/19/41/1'>詩 41:1</a> 〔大衛的詩，交與伶長。〕眷顧貧窮的有福了！他遭難的日子，耶和華必搭救他。<p><a href='/CUNP/20/19/17'>箴 19:17</a> 憐憫貧窮的，就是借給耶和華；他的善行，耶和華必償還。"
  },
  {
    "pk": 3488925,
    "translation": "CUNP",
    "book": 5,
    "chapter": 24,
    "verse": 20,
    "text": "你打橄欖樹，枝上剩下的，不可再打；要留給寄居的與孤兒寡婦。"
  },
  {
    "pk": 3488926,
    "translation": "CUNP",
    "book": 5,
    "chapter": 24,
    "verse": 21,
    "text": "你摘葡萄園的<i>葡萄</i>，所剩下的，不可再摘；要留給寄居的與孤兒寡婦。"
  },
  {
    "pk": 3488927,
    "translation": "CUNP",
    "book": 5,
    "chapter": 24,
    "verse": 22,
    "text": "你也要記念你在<e>埃及</e>地作過奴僕，所以我吩咐你這樣行。",
    "comment": "<a href='/CUNP/5/24/18'>申 24:18</a> 要記念你在<u>埃及</u>作過奴僕。耶和華──你的神從那裏將你救贖，所以我吩咐你這樣行。"
  }
]
