[
  {
    "pk": 3498894,
    "translation": "CUNP",
    "book": 19,
    "chapter": 101,
    "verse": 1,
    "text": "〔大衛的詩。〕<br/>我要歌唱慈愛和公平；耶和華啊，我要向你歌頌！<br/>",
    "comment": "<a href='/CUNP/19/89/1'>詩 89:1</a> 〔以斯拉人以探的訓誨詩。〕我要歌唱耶和華的慈愛，直到永遠；我要用口將你的信實傳與萬代。"
  },
  {
    "pk": 3498895,
    "translation": "CUNP",
    "book": 19,
    "chapter": 101,
    "verse": 2,
    "text": "我要用智慧行完全的道。你幾時到我這裏來呢？我要存完全的心行在我家中。<br/>",
    "comment": "<a href='/CUNP/9/18/14'>撒上 18:14</a> <u>大衛</u>做事無不精明，耶和華也與他同在。<br><a href='/CUNP/11/9/4'>王上 9:4</a> 你若效法你父<u>大衛</u>，存誠實正直的心行在我面前，遵行我一切所吩咐你的，謹守我的律例典章，<p><a href='/CUNP/11/11/4'>11:4</a> <u>所羅門</u>年老的時候，他的妃嬪誘惑他的心去隨從別神，不效法他父親<u>大衛</u>誠誠實實地順服耶和華──他的神。"
  },
  {
    "pk": 3498896,
    "translation": "CUNP",
    "book": 19,
    "chapter": 101,
    "verse": 3,
    "text": "邪僻的事，我都不擺在我眼前；悖逆人所做的事，我甚恨惡，不容沾在我身上。<br/>",
    "comment": "<a href='/CUNP/6/23/6'>書 23:6</a> 所以，你們要大大壯膽，謹守遵行寫在<u>摩西</u>律法書上的一切話，不可偏離左右。<p><a href='/CUNP/9/12/20-21'>撒上 12:20-21</a> <u>撒母耳</u>對百姓說：「不要懼怕！你們雖然行了這惡，卻不要偏離耶和華，只要盡心事奉他。若偏離<na>耶和華</na>去順從那不能救人的虛神是無益的。<p><a href='/CUNP/19/40/4'>詩 40:4</a> 那倚靠耶和華、不理會狂傲和偏向虛假之輩的，這人便為有福！<p><a href='/CUNP/19/125/5'>125:5</a> 至於那偏行彎曲道路的人，耶和華必使他和作惡的人一同出去<na>受刑</na>。願平安歸於<u>以色列</u>！<br><a href='/CUNP/19/97/10'>詩 97:10</a> 你們愛耶和華的，都當恨惡罪惡；他保護聖民的性命，搭救他們脫離惡人的手。"
  },
  {
    "pk": 3498897,
    "translation": "CUNP",
    "book": 19,
    "chapter": 101,
    "verse": 4,
    "text": "彎曲的心思，我必遠離；一切的惡人<sup>〔或作「惡事」〕</sup>，我不認識。<br/>",
    "comment": "<a href='/CUNP/40/7/23'>太 7:23</a> 我就明明地告訴他們說：『我從來不認識你們，你們這些作惡的人，離開我去吧！』」<p><a href='/CUNP/55/2/19'>提後 2:19</a> 然而，神堅固的根基立住了；上面有這印記說：「主認識誰是他的人」；又說：「凡稱呼主名的人總要離開不義。」"
  },
  {
    "pk": 3498898,
    "translation": "CUNP",
    "book": 19,
    "chapter": 101,
    "verse": 5,
    "text": "在暗中讒謗他鄰居的，我必將他滅絕；眼目高傲、心裏驕縱的，我必不容他。",
    "comment": "<a href='/CUNP/19/18/27'>詩 18:27</a> 困苦的百姓，你必拯救；高傲的眼目，你必使他降卑。<p><a href='/CUNP/20/6/17'>箴 6:17</a> 就是高傲的眼，撒謊的舌，流無辜人血的手，"
  },
  {
    "pk": 3498899,
    "translation": "CUNP",
    "book": 19,
    "chapter": 101,
    "verse": 6,
    "text": "我眼要看國中的誠實人，叫他們與我同住；行為完全的，他要伺候我。<br/>"
  },
  {
    "pk": 3498900,
    "translation": "CUNP",
    "book": 19,
    "chapter": 101,
    "verse": 7,
    "text": "行詭詐的，必不得住在我家裏；說謊話的，必不得立在我眼前。<br/>"
  },
  {
    "pk": 3498901,
    "translation": "CUNP",
    "book": 19,
    "chapter": 101,
    "verse": 8,
    "text": "我每日早晨要滅絕國中所有的惡人，好把一切作孽的從耶和華的城裏剪除。",
    "comment": "<a href='/CUNP/19/48/2'>詩 48:2</a>, <a href='/CUNP/19/48/8'>8</a> <u>錫安山</u>──大君王的城，在北面居高華美，為全地所喜悅。……我們在萬軍之耶和華的城中──就是我們神的城中──所看見的，正如我們所聽見的。神必堅立這城，直到永遠。（細拉）<br><a href='/CUNP/19/75/10'>詩 75:10</a> 惡人一切的角，我要砍斷；惟有義人的角必被高舉。<p><a href='/CUNP/24/21/12'>耶 21:12</a> <u>大衛</u>家啊，耶和華如此說：你們每早晨要施行公平，拯救被搶奪的脫離欺壓人的手，恐怕我的忿怒因你們的惡行發作，如火著起，甚至無人能以熄滅。"
  }
]
