[
  {
    "pk": 3499611,
    "translation": "CUNP",
    "book": 19,
    "chapter": 138,
    "verse": 1,
    "text": "〔大衛的詩。〕<br/>我要一心稱謝你，在諸神面前歌頌你。<br/>",
    "comment": "<a href='/CUNP/19/119/46'>詩 119:46</a> 我也要在君王面前論說你的法度，並不至於羞愧。"
  },
  {
    "pk": 3499612,
    "translation": "CUNP",
    "book": 19,
    "chapter": 138,
    "verse": 2,
    "text": "我要向你的聖殿下拜，為你的慈愛和誠實稱讚你的名；因你使你的話顯為大，過於你所應許的<sup>〔或作「超乎你的名聲」〕</sup>。<br/>",
    "comment": "<a href='/CUNP/23/42/21'>賽 42:21</a> 耶和華因自己公義的緣故，喜歡使律法<small>〔或作「訓誨」〕</small>為大，為尊。<br><a href='/CUNP/11/8/29-30'>王上 8:29-30</a> 願你晝夜看顧這殿，就是你應許立為你名的居所；求你垂聽僕人向此處禱告的話。你僕人和你民<u>以色列</u>向此處祈禱的時候，求你在天上你的居所垂聽，垂聽而赦免。<p><a href='/CUNP/19/5/7'>詩 5:7</a> 至於我，我必憑你豐盛的慈愛進入你的居所；我必存敬畏你的心向你的聖殿下拜。<br><a href='/CUNP/19/28/2'>詩 28:2</a> 我呼求你，向你至聖所舉手的時候，求你垂聽我懇求的聲音！"
  },
  {
    "pk": 3499613,
    "translation": "CUNP",
    "book": 19,
    "chapter": 138,
    "verse": 3,
    "text": "我呼求的日子，你就應允我，鼓勵我，使我心裏有能力。"
  },
  {
    "pk": 3499614,
    "translation": "CUNP",
    "book": 19,
    "chapter": 138,
    "verse": 4,
    "text": "耶和華啊，地上的君王都要稱謝你，因他們聽見了你口中的言語。<br/>",
    "comment": "<a href='/CUNP/19/102/15'>詩 102:15</a>, <a href='/CUNP/19/102/22'>22</a> 列國要敬畏耶和華的名；世上諸王都敬畏你的榮耀。……就是在萬民和列國聚會事奉耶和華的時候。"
  },
  {
    "pk": 3499615,
    "translation": "CUNP",
    "book": 19,
    "chapter": 138,
    "verse": 5,
    "text": "他們要歌頌耶和華的作為，因耶和華大有榮耀。<br/>"
  },
  {
    "pk": 3499616,
    "translation": "CUNP",
    "book": 19,
    "chapter": 138,
    "verse": 6,
    "text": "耶和華雖高，仍看顧低微的人；他卻從遠處看出驕傲的人。",
    "comment": "<a href='/CUNP/19/113/5-6'>詩 113:5-6</a> 誰像耶和華──我們的神呢？他坐在至高之處，自己謙卑，觀看天上地下的事。<p><a href='/CUNP/23/57/15'>賽 57:15</a> 因為那至高至上、永遠長存<small>〔原文作「住在永遠」〕</small>名為聖者的如此說：我住在至高至聖的所在，也與心靈痛悔謙卑的人同居；要使謙卑人的靈甦醒，也使痛悔人的心甦醒。<br><a href='/CUNP/20/3/34'>箴 3:34</a> 他譏誚那好譏誚的人，賜恩給謙卑的人。<p><a href='/CUNP/59/4/6'>雅 4:6</a> 但他賜更多的恩典，所以經上說：神阻擋驕傲的人，賜恩給謙卑的人。<p><a href='/CUNP/60/5/5'>彼前 5:5</a> 你們年幼的，也要順服年長的。就是你們眾人也都要以謙卑束腰，彼此順服；因為神阻擋驕傲的人，賜恩給謙卑的人。"
  },
  {
    "pk": 3499617,
    "translation": "CUNP",
    "book": 19,
    "chapter": 138,
    "verse": 7,
    "text": "我雖行在患難中，你必將我救活；我的仇敵發怒，你必伸手抵擋他們；你的右手也必救我。<br/>",
    "comment": "<a href='/CUNP/19/23/3-4'>詩 23:3-4</a> 他使我的靈魂甦醒，為自己的名引導我走義路。我雖然行過死蔭的<na>幽</na>谷，也不怕遭害，因為你與我同在；你的杖，你的竿，都安慰我。"
  },
  {
    "pk": 3499618,
    "translation": "CUNP",
    "book": 19,
    "chapter": 138,
    "verse": 8,
    "text": "耶和華必成全關乎我的事；耶和華啊，你的慈愛永遠長存！求你不要離棄你手所造的。",
    "comment": "參看 <a href='/CUNP/18/10/3'>伯 10:3</a>, <a href='/CUNP/18/10/8'>8</a> 你手所造的，你又欺壓，又藐視，卻光照惡人的計謀。這事你以為美嗎？……你的手創造我，造就我的四肢百體，你還要毀滅我。<p><a href='/CUNP/18/14/15'>14:15</a> 你呼叫，我便回答；你手所做的，你必羨慕。<br><a href='/CUNP/19/57/2'>詩 57:2</a> 我要求告至高的神，就是為我成全<na>諸事</na>的神。<p><a href='/CUNP/50/1/6'>腓 1:6</a> 我深信那在你們心裏動了善工的，必成全這工，直到耶穌基督的日子。"
  }
]
