[
  {
    "pk": 3511495,
    "translation": "CUNP",
    "book": 45,
    "chapter": 8,
    "verse": 1,
    "text": "如今，那些在基督耶穌裏的就不定罪了。",
    "comment": "<a href='/CUNP/45/8/4'>羅 8:4</a> 使律法的義成就在我們這不隨從肉體、只隨從<na>聖</na>靈的人身上。<p><a href='/CUNP/48/5/16'>加 5:16</a>, <a href='/CUNP/48/5/25'>25</a> 我說，你們當順著<na>聖</na>靈而行，就不放縱肉體的情慾了。……我們若是靠<na>聖</na>靈得生，就當靠<na>聖</na>靈行事。"
  },
  {
    "pk": 3511496,
    "translation": "CUNP",
    "book": 45,
    "chapter": 8,
    "verse": 2,
    "text": "因為賜生命<i>聖</i>靈的律，在基督耶穌裏釋放了我，使我脫離罪和死的律了。",
    "comment": "<a href='/CUNP/43/8/36'>約 8:36</a> 所以<na>天父的</na>兒子若叫你們自由，你們就真自由了。<p><a href='/CUNP/45/6/18'>羅 6:18</a>, <a href='/CUNP/45/6/22'>22</a> 你們既從罪裏得了釋放，就作了義的奴僕。……但現今，你們既從罪裏得了釋放，作了神的奴僕，就有成聖的果子，那結局就是永生。<p><a href='/CUNP/48/2/19'>加 2:19</a> 我因律法，就向律法死了，叫我可以向神活著。<p><a href='/CUNP/48/5/1'>5:1</a> 基督釋放了我們，叫我們得以自由。所以要站立得穩，不要再被奴僕的軛挾制。<br><a href='/CUNP/45/7/24-25'>羅 7:24-25</a> 我真是苦啊！誰能救我脫離這取死的身體呢？感謝神，靠著我們的主耶穌基督<na>就能脫離了</na>。這樣看來，我以內心順服神的律，我肉體卻順服罪的律了。<br><a href='/CUNP/46/15/45'>林前 15:45</a> <na>經上</na>也是這樣記著說：「首先的人<u>亞當</u>成了有靈的活人<small>〔「靈」或作「血氣」〕</small>」；末後的<u>亞當</u>成了叫人活的靈。<p><a href='/CUNP/47/3/6'>林後 3:6</a> 他叫我們能承當這新約的執事，不是憑著字句，乃是憑著精意；因為那字句是叫人死，精意是叫人活<small>〔「精意」或作「聖靈」〕</small>。"
  },
  {
    "pk": 3511497,
    "translation": "CUNP",
    "book": 45,
    "chapter": 8,
    "verse": 3,
    "text": "律法既因肉體軟弱，有所不能行的，神就差遣自己的兒子，成為罪身的形狀，作了贖罪祭，在肉體中定了罪案，",
    "comment": "<a href='/CUNP/48/3/13'>加 3:13</a> 基督既為我們受了咒詛，就贖出我們脫離律法的咒詛；因為<na>經上</na>記著：「凡掛在木頭上都是被咒詛<small>〔「受」原文作「成」〕</small>的。」<p><a href='/CUNP/47/5/21'>林後 5:21</a> 神使那無罪的<small>〔「無罪」原文作「不知罪」〕</small>，替我們成為罪，好叫我們在他裏面成為神的義。<br><a href='/CUNP/44/13/39'>徒 13:39</a> 你們靠<u>摩西</u>的律法，在一切不得稱義的事上信靠這人，就都得稱義了。<p><a href='/CUNP/45/3/20'>羅 3:20</a> 所以凡有血氣的，沒有一個因行律法能在神面前稱義，因為律法本是叫人知罪。<p><a href='/CUNP/58/7/18-19'>來 7:18-19</a> 先前的條例，因軟弱無益，所以廢掉了，（律法原來一無所成）就引進了更美的指望；靠這指望，我們便可以進到神面前。<p><a href='/CUNP/58/10/1-2'>10:1-2</a>, <a href='/CUNP/58/10/10'>10</a>, <a href='/CUNP/58/10/14'>14</a> 律法既是將來美事的影兒，不是本物的真像，總不能藉著每年常獻一樣的祭物叫那近前來的人得以完全。若不然，獻祭的事豈不早已止住了嗎？因為禮拜的人，良心既被潔淨，就不再覺得有罪了。……我們憑這旨意，靠耶穌基督，只一次獻上他的身體，就得以成聖。……因為他一次獻祭，便叫那得以成聖的人永遠完全。"
  },
  {
    "pk": 3511498,
    "translation": "CUNP",
    "book": 45,
    "chapter": 8,
    "verse": 4,
    "text": "使律法的義成就在我們這不隨從肉體、只隨從<i>聖</i>靈的人身上。",
    "comment": "<a href='/CUNP/45/8/1'>羅 8:1</a> 如今，那些在基督耶穌裏的就不定罪了。"
  },
  {
    "pk": 3511499,
    "translation": "CUNP",
    "book": 45,
    "chapter": 8,
    "verse": 5,
    "text": "因為，隨從肉體的人體貼肉體的事；隨從<i>聖</i>靈的人體貼<i>聖</i>靈的事。",
    "comment": "<a href='/CUNP/48/5/22'>加 5:22</a>, <a href='/CUNP/48/5/25'>25</a> 聖靈所結的果子，就是仁愛、喜樂、和平、忍耐、恩慈、良善、信實、……我們若是靠<na>聖</na>靈得生，就當靠<na>聖</na>靈行事。<br><a href='/CUNP/43/3/6'>約 3:6</a> 從肉身生的就是肉身；從靈生的就是靈。<p><a href='/CUNP/46/2/14'>林前 2:14</a> 然而，屬血氣的人不領會神<na>聖</na>靈的事，反倒以為愚拙，並且不能知道，因為這些事惟有屬靈的人才能看透。"
  },
  {
    "pk": 3511500,
    "translation": "CUNP",
    "book": 45,
    "chapter": 8,
    "verse": 6,
    "text": "體貼肉體的，就是死；體貼<i>聖</i>靈的，乃是生命、平安。",
    "comment": "<a href='/CUNP/45/6/21'>羅 6:21</a> 你們現今所看為羞恥的事，當日有甚麼果子呢？那些事的結局就是死。<p><a href='/CUNP/45/8/13'>8:13</a> 你們若順從肉體活著，必要死；若靠著<na>聖</na>靈治死身體的惡行，必要活著。<p><a href='/CUNP/48/6/8'>加 6:8</a> 順著情慾撒種的，必從情慾收敗壞；順著<na>聖</na>靈撒種的，必從<na>聖</na>靈收永生。"
  },
  {
    "pk": 3511501,
    "translation": "CUNP",
    "book": 45,
    "chapter": 8,
    "verse": 7,
    "text": "原來體貼肉體的，就是與神為仇；因為不服神的律法，也是不能服，",
    "comment": "<a href='/CUNP/59/4/4'>雅 4:4</a> 你們這些淫亂的人哪<small>〔「淫亂的人」原文作「淫婦」〕</small>，豈不知與世俗為友就是與神為敵嗎？所以凡想要與世俗為友的，就是與神為敵了。<br><a href='/CUNP/46/2/14'>林前 2:14</a> 然而，屬血氣的人不領會神<na>聖</na>靈的事，反倒以為愚拙，並且不能知道，因為這些事惟有屬靈的人才能看透。"
  },
  {
    "pk": 3511502,
    "translation": "CUNP",
    "book": 45,
    "chapter": 8,
    "verse": 8,
    "text": "而且屬肉體的人不能得神的喜歡。"
  },
  {
    "pk": 3511503,
    "translation": "CUNP",
    "book": 45,
    "chapter": 8,
    "verse": 9,
    "text": "如果神的靈住在你們心裏，你們就不屬肉體，乃屬<i>聖</i>靈了。人若沒有基督的靈，就不是屬基督的。",
    "comment": "<a href='/CUNP/46/3/16'>林前 3:16</a> 豈不知你們是神的殿，神的靈住在你們裏頭嗎？<p><a href='/CUNP/46/6/19'>6:19</a> 豈不知你們的身子就是聖靈的殿嗎？這聖靈是從神而來，住在你們裏頭的；並且你們不是自己的人，<br><a href='/CUNP/43/3/34'>約 3:34</a> 神所差來的就說神的話，因為神賜<na>聖</na>靈<na>給他</na>是沒有限量的。<p><a href='/CUNP/48/4/6'>加 4:6</a> 你們既為兒子，神就差他兒子的靈進入你們<small>〔原文作「我們」〕</small>的心，呼叫：「阿爸！父！」<p><a href='/CUNP/50/1/19'>腓 1:19</a> 因為我知道，這事藉著你們的祈禱和耶穌基督之靈的幫助，終必叫我得救。<p><a href='/CUNP/60/1/11'>彼前 1:11</a> 就是考察在他們心裏基督的靈，預先證明基督受苦難，後來得榮耀，是指著甚麼時候，並怎樣的時候。"
  },
  {
    "pk": 3511504,
    "translation": "CUNP",
    "book": 45,
    "chapter": 8,
    "verse": 10,
    "text": "基督若在你們心裏，身體就因罪而死，心靈卻因義而活。"
  },
  {
    "pk": 3511505,
    "translation": "CUNP",
    "book": 45,
    "chapter": 8,
    "verse": 11,
    "text": "然而，叫耶穌從死裏復活者的靈若住在你們心裏，那叫基督耶穌從死裏復活的，也必藉著住在你們心裏的<i>聖</i>靈，使你們必死的身體又活過來。",
    "comment": "<a href='/CUNP/44/2/24'>徒 2:24</a> 神卻將死的痛苦解釋了，叫他復活，因為他原不能被死拘禁。<br><a href='/CUNP/45/6/4-5'>羅 6:4-5</a> 所以，我們藉著洗禮歸入死，和他一同埋葬，原是叫我們一舉一動有新生的樣式，像基督藉著父的榮耀從死裏復活一樣。我們若在他死的形狀上與他聯合，也要在他復活的形狀上與他聯合；<p><a href='/CUNP/46/6/14'>林前 6:14</a> 並且神已經叫主復活，也要用自己的能力叫我們復活。<p><a href='/CUNP/47/4/14'>林後 4:14</a> 自己知道那叫主耶穌復活的，也必叫我們與耶穌一同復活，並且叫我們與你們一同站在他面前。<p><a href='/CUNP/49/2/5'>弗 2:5</a> 當我們死在過犯中的時候，便叫我們與基督一同活過來<small>〔你們得救是本乎恩〕</small>。你們得救是本乎恩。"
  },
  {
    "pk": 3511506,
    "translation": "CUNP",
    "book": 45,
    "chapter": 8,
    "verse": 12,
    "text": "弟兄們，這樣看來，我們並不是欠肉體的債去順從肉體活著。",
    "comment": "<a href='/CUNP/45/6/7'>羅 6:7</a>, <a href='/CUNP/45/6/14'>14</a> 因為已死的人是脫離了罪。……罪必不能作你們的主；因你們不在律法之下，乃在恩典之下。"
  },
  {
    "pk": 3511507,
    "translation": "CUNP",
    "book": 45,
    "chapter": 8,
    "verse": 13,
    "text": "你們若順從肉體活著，必要死；若靠著<i>聖</i>靈治死身體的惡行，必要活著。",
    "comment": "<a href='/CUNP/49/4/22'>弗 4:22</a> 就要脫去你們從前行為上的舊人，這舊人是因私慾的迷惑漸漸變壞的；<p><a href='/CUNP/51/3/5'>西 3:5</a> 所以，要治死你們在地上的肢體，就如淫亂、污穢、邪情、惡慾，和貪婪（貪婪<small>〔貪婪就與拜偶像一樣〕</small>就與拜偶像一樣）。<br><a href='/CUNP/45/8/6'>羅 8:6</a> 體貼肉體的，就是死；體貼<na>聖</na>靈的，乃是生命、平安。<p><a href='/CUNP/48/6/8'>加 6:8</a> 順著情慾撒種的，必從情慾收敗壞；順著<na>聖</na>靈撒種的，必從<na>聖</na>靈收永生。"
  },
  {
    "pk": 3511508,
    "translation": "CUNP",
    "book": 45,
    "chapter": 8,
    "verse": 14,
    "text": "因為凡被神的靈引導的，都是神的兒子。",
    "comment": "<a href='/CUNP/48/5/18'>加 5:18</a> 但你們若被<na>聖</na>靈引導，就不在律法以下。"
  },
  {
    "pk": 3511509,
    "translation": "CUNP",
    "book": 45,
    "chapter": 8,
    "verse": 15,
    "text": "你們所受的，不是奴僕的心，仍舊害怕；所受的，乃是兒子的心，因此我們呼叫：「阿爸！父！」",
    "comment": "<a href='/CUNP/55/1/7'>提後 1:7</a> 因為神賜給我們，不是膽怯的心，乃是剛強、仁愛、謹守的心。<p><a href='/CUNP/62/4/18'>約壹 4:18</a> 愛裏沒有懼怕；愛既完全，就把懼怕除去。因為懼怕裏含著刑罰，懼怕的人在愛裏未得完全。<br><a href='/CUNP/46/2/12'>林前 2:12</a> 我們所領受的，並不是世上的靈，乃是從神來的靈，叫我們能知道神開恩賜給我們的事。<p><a href='/CUNP/58/2/15'>來 2:15</a> 並要釋放那些一生因怕死而為奴僕的人。<br><a href='/CUNP/23/56/5'>賽 56:5</a> 我必使他們在我殿中，在我牆內，有記念，有名號，比有兒女的更美。我必賜他們永遠的名，不能剪除。<p><a href='/CUNP/48/4/5-6'>加 4:5-6</a> 要把律法以下的人贖出來，叫我們得著兒子的名分。你們既為兒子，神就差他兒子的靈進入你們<small>〔原文作「我們」〕</small>的心，呼叫：「阿爸！父！」<br><a href='/CUNP/41/14/36'>可 14:36</a> 他說：「阿爸！父啊！在你凡事都能；求你將這杯撤去。然而，不要從我的意思，只要從你的意思。」"
  },
  {
    "pk": 3511510,
    "translation": "CUNP",
    "book": 45,
    "chapter": 8,
    "verse": 16,
    "text": "聖靈與我們的心同證我們是神的兒女；",
    "comment": "<a href='/CUNP/47/1/22'>林後 1:22</a> 他又用印印了我們，並賜<na>聖</na>靈在我們心裏作憑據<small>〔原文作「質」〕</small>。<p><a href='/CUNP/47/5/5'>5:5</a> 為此，培植我們的就是神，他又賜給我們<na>聖</na>靈作憑據<small>〔原文作「質」〕</small>。<p><a href='/CUNP/49/1/13'>弗 1:13</a> 你們既聽見真理的道，就是那叫你們得救的福音，也<na>信了</na>基督，既然信他，就受了所應許的聖靈為印記。<p><a href='/CUNP/49/4/30'>4:30</a> 不要叫神的聖靈擔憂；你們原是受了他的印記，等候得贖的日子來到。"
  },
  {
    "pk": 3511511,
    "translation": "CUNP",
    "book": 45,
    "chapter": 8,
    "verse": 17,
    "text": "既是兒女，便是後嗣，就是神的後嗣，和基督同作後嗣。如果我們和他一同受苦，也必和他一同得榮耀。",
    "comment": "<a href='/CUNP/44/26/18'>徒 26:18</a> 我差你到他們那裏去，要叫他們的眼睛得開，從黑暗中歸向光明，從撒但權下歸向神；又因信我，得蒙赦罪，和一切成聖的人同得基業。』」<p><a href='/CUNP/48/4/7'>加 4:7</a> 可見，從此以後，你不是奴僕，乃是兒子了；既是兒子，就靠著神為後嗣。<br><a href='/CUNP/44/14/22'>徒 14:22</a> 堅固門徒的心，勸他們恆守所信的道；又說：「我們進入神的國，必須經歷許多艱難。」<p><a href='/CUNP/50/1/29'>腓 1:29</a> 因為你們蒙恩，不但得以信服基督，並要為他受苦。<p><a href='/CUNP/55/2/11-12'>提後 2:11-12</a> 有可信的話說：我們若與基督同死，也必與他同活；我們若<na>能</na>忍耐，也必和他一同作王。我們若不認他，他也必不認我們；"
  },
  {
    "pk": 3511512,
    "translation": "CUNP",
    "book": 45,
    "chapter": 8,
    "verse": 18,
    "text": "我想，現在的苦楚若比起將來要顯於我們的榮耀就不足介意了。",
    "comment": "<a href='/CUNP/47/4/17'>林後 4:17</a> 我們這至暫至輕的苦楚，要為我們成就極重無比、永遠的榮耀。<p><a href='/CUNP/60/1/6-7'>彼前 1:6-7</a> 因此，你們是大有喜樂；但如今，在百般的試煉中暫時憂愁，叫你們的信心既被試驗，就比那被火試驗仍然能壞的金子更顯寶貴，可以在耶穌基督顯現的時候得著稱讚、榮耀、尊貴。<p><a href='/CUNP/60/4/13'>4:13</a> 倒要歡喜；因為你們是與基督一同受苦，使你們在他榮耀顯現的時候，也可以歡喜快樂。"
  },
  {
    "pk": 3511513,
    "translation": "CUNP",
    "book": 45,
    "chapter": 8,
    "verse": 19,
    "text": "受造之物切望等候神的眾子顯出來。",
    "comment": "<a href='/CUNP/62/3/2'>約壹 3:2</a> 親愛的<na>弟兄</na>啊，我們現在是神的兒女，將來如何，還未顯明；但我們知道，主若顯現，我們必要像他，因為必得見他的真體。<br><a href='/CUNP/61/3/13'>彼後 3:13</a> 但我們照他的應許，盼望新天新地，有義居在其中。"
  },
  {
    "pk": 3511514,
    "translation": "CUNP",
    "book": 45,
    "chapter": 8,
    "verse": 20,
    "text": "因為受造之物服在虛空之下，不是自己願意，乃是因那叫他如此的。",
    "comment": "<a href='/CUNP/45/8/22'>羅 8:22</a> 我們知道，一切受造之物一同歎息，勞苦，直到如今。<p><a href='/CUNP/1/3/19'>創 3:19</a> 你必汗流滿面才得糊口，直到你歸了土，因為你是從土而出的。你本是塵土，仍要歸於塵土。"
  },
  {
    "pk": 3511515,
    "translation": "CUNP",
    "book": 45,
    "chapter": 8,
    "verse": 21,
    "text": "但受造之物仍然指望脫離敗壞的轄制，得享神兒女自由的榮耀<sup>〔「享」原文作「入」〕</sup>。"
  },
  {
    "pk": 3511516,
    "translation": "CUNP",
    "book": 45,
    "chapter": 8,
    "verse": 22,
    "text": "我們知道，一切受造之物一同歎息，勞苦，直到如今。",
    "comment": "<a href='/CUNP/24/12/11'>耶 12:11</a> 他們使地荒涼；地既荒涼，便向我悲哀。全地荒涼，因無人介意。"
  },
  {
    "pk": 3511517,
    "translation": "CUNP",
    "book": 45,
    "chapter": 8,
    "verse": 23,
    "text": "不但如此，就是我們這有<i>聖</i>靈初結果子的，也是自己心裏歎息，等候得著兒子的名分，乃是我們的身體得贖。",
    "comment": "<a href='/CUNP/47/5/5'>林後 5:5</a> 為此，培植我們的就是神，他又賜給我們<na>聖</na>靈作憑據<small>〔原文作「質」〕</small>。<p><a href='/CUNP/49/1/14'>弗 1:14</a> 這聖靈是我們得基業的憑據<small>〔原文作「質」〕</small>，直等到<na>神</na>之民<small>〔「民」原文作「產業」〕</small>被贖，使他的榮耀得著稱讚。<br><a href='/CUNP/47/5/2'>林後 5:2</a>, <a href='/CUNP/47/5/4'>4</a> 我們在這帳棚裏歎息，深想得那從天上來的房屋，好像穿上<na>衣服</na>；……我們在這帳棚裏歎息勞苦，並非願意脫下這個，乃是願意穿上那個，好叫這必死的被生命吞滅了。<br><a href='/CUNP/42/20/36'>路 20:36</a> 因為他們不能再死，和天使一樣；既是復活的人，就為神的兒子。<br><a href='/CUNP/42/21/28'>路 21:28</a> 一有這些事，你們就當挺身昂首，因為你們得贖的日子近了。」<p><a href='/CUNP/49/4/30'>弗 4:30</a> 不要叫神的聖靈擔憂；你們原是受了他的印記，等候得贖的日子來到。"
  },
  {
    "pk": 3511518,
    "translation": "CUNP",
    "book": 45,
    "chapter": 8,
    "verse": 24,
    "text": "我們得救是在乎盼望；只是所見的盼望不是盼望，誰還盼望他所見的呢<sup>〔有古卷作「人所看見的何必再盼望呢？」〕</sup>？",
    "comment": "<a href='/CUNP/47/5/7'>林後 5:7</a> 因我們行事為人是憑著信心，不是憑著眼見。<p><a href='/CUNP/58/11/1'>來 11:1</a> 信就是所望之事的實底，是未見之事的確據。"
  },
  {
    "pk": 3511519,
    "translation": "CUNP",
    "book": 45,
    "chapter": 8,
    "verse": 25,
    "text": "但我們若盼望那所不見的，就必忍耐等候。"
  },
  {
    "pk": 3511520,
    "translation": "CUNP",
    "book": 45,
    "chapter": 8,
    "verse": 26,
    "text": "況且，我們的軟弱有<i>聖</i>靈幫助；我們本不曉得當怎樣禱告，只是<i>聖</i>靈親自用說不出來的歎息替我們禱告。",
    "comment": "<a href='/CUNP/38/12/10'>亞 12:10</a>「我必將那施恩叫人懇求的靈，澆灌<u>大衛</u>家和<u>耶路撒冷</u>的居民。他們必仰望我<small>〔或作「他本節同」〕</small>，就是他們所扎的；必為我悲哀，如喪獨生子，又為我愁苦，如喪長子。<p><a href='/CUNP/49/6/18'>弗 6:18</a> 靠著<na>聖</na>靈，隨時多方禱告祈求；並要在此警醒不倦，為眾聖徒祈求，<br><a href='/CUNP/40/20/22'>太 20:22</a> 耶穌回答說：「你們不知道所求的是甚麼；我將要喝的杯，你們能喝嗎？」他們說：「我們能。」<p><a href='/CUNP/59/4/3'>雅 4:3</a> 你們求也得不著，是因為你們妄求，要浪費在你們的宴樂中。"
  },
  {
    "pk": 3511521,
    "translation": "CUNP",
    "book": 45,
    "chapter": 8,
    "verse": 27,
    "text": "鑒察人心的，曉得<i>聖</i>靈的意思，因為<i>聖</i>靈照著神的<i>旨意</i>替聖徒祈求。",
    "comment": "<a href='/CUNP/62/5/14'>約壹 5:14</a> 我們若照他的旨意求甚麼，他就聽我們，這是我們向他所存坦然無懼的心。<br><a href='/CUNP/13/28/9'>代上 28:9</a>「我兒<u>所羅門</u>哪，你當認識耶和華──你父的神，誠心樂意地事奉他；因為他鑒察眾人的心，知道一切心思意念。你若尋求他，他必使你尋見；你若離棄他，他必永遠丟棄你。<p><a href='/CUNP/19/7/9'>詩 7:9</a> 願惡人的惡斷絕！願你堅立義人！因為公義的神察驗人的心腸肺腑。<p><a href='/CUNP/20/17/3'>箴 17:3</a> 鼎為煉銀，爐為煉金；惟有耶和華熬煉人心。<p><a href='/CUNP/24/11/20'>耶 11:20</a> 按公義判斷、察驗人肺腑心腸的萬軍之耶和華啊，我卻要見你在他們身上報仇，因我將我的案件向你稟明了。<p><a href='/CUNP/24/17/10'>17:10</a> 我──耶和華是鑒察人心、試驗人肺腑的，要照各人所行的和他做事的結果報應他。<p><a href='/CUNP/24/20/12'>20:12</a> 試驗義人、察看人肺腑心腸的萬軍之耶和華啊，求你容我見你在他們身上報仇，因我將我的案件向你稟明了。<p><a href='/CUNP/44/1/24'>徒 1:24</a> 眾人就禱告說：「主啊，你知道萬人的心，求你從這兩個人中，指明你所揀選的是誰，叫他得這使徒的位分。這位分<u>猶大</u>已經丟棄，往自己的地方去了。」<p><a href='/CUNP/52/2/4'>帖前 2:4</a> 但神既然驗中了我們，把福音託付我們，我們就照樣講，不是要討人喜歡，乃是要討那察驗我們心的神喜歡。<p><a href='/CUNP/66/2/23'>啟 2:23</a> 我又要殺死她的黨類<small>〔「黨類」原文作「兒女」〕</small>，叫眾教會知道，我是那察看人肺腑心腸的，並要照你們的行為報應你們各人。"
  },
  {
    "pk": 3511522,
    "translation": "CUNP",
    "book": 45,
    "chapter": 8,
    "verse": 28,
    "text": "我們曉得萬事都互相效力，叫愛神的人得益處，就是按他旨意被召的人。",
    "comment": "<a href='/CUNP/45/9/11'>羅 9:11</a>, <a href='/CUNP/45/9/23-24'>23-24</a> （<na>雙子</na>還沒有生下來，善惡還沒有做出來，只因要顯明神揀選人的旨意，不在乎人的行為，乃在乎召人的<na>主</na>。）……又要將他豐盛的榮耀彰顯在那蒙憐憫、早預備得榮耀的器皿上。這<na>器皿</na>就是我們被神所召的，不但是從<u>猶太</u>人中，也是從外邦人中。這有甚麼不可呢？<p><a href='/CUNP/55/1/9'>提後 1:9</a> 神救了我們，以聖召召我們，不是按我們的行為，乃是按他的旨意和恩典；這恩典是萬古之先，在基督耶穌裏賜給我們的，"
  },
  {
    "pk": 3511523,
    "translation": "CUNP",
    "book": 45,
    "chapter": 8,
    "verse": 29,
    "text": "因為他預先所知道的人，就預先定下效法他兒子的模樣，使他兒子在許多弟兄中作長子。",
    "comment": "<a href='/CUNP/43/17/22'>約 17:22</a> 你所賜給我的榮耀，我已賜給他們，使他們合而為一，像我們合而為一。<p><a href='/CUNP/47/3/18'>林後 3:18</a> 我們眾人既然敞著臉得以看見主的榮光，好像從鏡子裏返照，就變成主的形狀，榮上加榮，如同從主的靈變成的。<p><a href='/CUNP/50/3/21'>腓 3:21</a> 他要按著那能叫萬有歸服自己的大能，將我們這卑賤的身體改變形狀，和他自己榮耀的身體相似。<p><a href='/CUNP/62/3/2'>約壹 3:2</a> 親愛的<na>弟兄</na>啊，我們現在是神的兒女，將來如何，還未顯明；但我們知道，主若顯現，我們必要像他，因為必得見他的真體。<br><a href='/CUNP/51/1/15'>西 1:15</a>, <a href='/CUNP/51/1/18'>18</a> 愛子是那不能看見之神的像，是首生的，在一切被造的以先。……他也是教會全體之首。他是元始，是從死裏首先復生的，使他可以在凡事上居首位。<p><a href='/CUNP/58/1/6'>來 1:6</a> 再者，神使長子到世上來的時候<small>〔或作「神再使長子到世上來的時候」〕</small>，就說：神的使者都要拜他。<p><a href='/CUNP/66/1/5'>啟 1:5</a> 並那誠實作見證的、從死裏首先復活、為世上君王元首的耶穌基督，有恩惠、平安歸與你們！他愛我們，用自己的血使我們脫離罪惡，<br>參看 <a href='/CUNP/2/33/12'>出 33:12</a>, <a href='/CUNP/2/33/17'>17</a> <u>摩西</u>對耶和華說：「你吩咐我說：『將這百姓領上去』，卻沒有叫我知道你要打發誰與我同去，只說：『我按你的名認識你，你在我眼前也蒙了恩。』……耶和華對<u>摩西</u>說：「你這所求的我也要行；因為你在我眼前蒙了恩，並且我按你的名認識你。」<p><a href='/CUNP/19/1/6'>詩 1:6</a> 因為耶和華知道義人的道路；惡人的道路卻必滅亡。<p><a href='/CUNP/24/1/5'>耶 1:5</a> 我未將你造在腹中，我已曉得你；你未出母胎，我已分別你為聖；我已派你作列國的先知。<p><a href='/CUNP/40/7/23'>太 7:23</a> 我就明明地告訴他們說：『我從來不認識你們，你們這些作惡的人，離開我去吧！』」<p><a href='/CUNP/45/11/2'>羅 11:2</a> 神並沒有棄絕他預先所知道的百姓。你們豈不曉得經上論到<u>以利亞</u>是怎麼說的呢？他在神面前怎樣控告<u>以色列</u>人說：<p><a href='/CUNP/55/2/19'>提後 2:19</a> 然而，神堅固的根基立住了；上面有這印記說：「主認識誰是他的人」；又說：「凡稱呼主名的人總要離開不義。」<p><a href='/CUNP/60/1/2'>彼前 1:2</a> 就是照父神的先見被揀選，藉著<na>聖</na>靈得成聖潔，以致順服耶穌基督，又蒙他血所灑的人。願恩惠、平安多多地加給你們。<br><a href='/CUNP/49/1/5'>弗 1:5</a>, <a href='/CUNP/49/1/11'>11</a> 又因愛我們，就按著自己的意旨所喜悅的，預定我們藉著耶穌基督得兒子的名分，……我們也在他裏面得了基業<small>〔「得」或作「成」〕</small>；這原是那位隨己意行、做萬事的，照著他旨意所預定的，"
  },
  {
    "pk": 3511524,
    "translation": "CUNP",
    "book": 45,
    "chapter": 8,
    "verse": 30,
    "text": "預先所定下的人又召他們來；所召來的人又稱他們為義；所稱為義的人又叫他們得榮耀。",
    "comment": "<a href='/CUNP/45/1/6'>羅 1:6</a> 其中也有你們這蒙召屬耶穌基督的人。<p><a href='/CUNP/45/9/24'>9:24</a> 這<na>器皿</na>就是我們被神所召的，不但是從<u>猶太</u>人中，也是從外邦人中。這有甚麼不可呢？<p><a href='/CUNP/49/4/4'>弗 4:4</a> 身體只有一個，<na>聖</na>靈只有一個，正如你們蒙召同有一個指望。<p><a href='/CUNP/58/9/15'>來 9:15</a> 為此，他作了新約的中保，既然受死贖了人在前約之時所犯的罪過，便叫蒙召之人得著所應許永遠的產業。<p><a href='/CUNP/60/2/9'>彼前 2:9</a> 惟有你們是被揀選的族類，是有君尊的祭司，是聖潔的國度，是屬<na>神</na>的子民，要叫你們宣揚那召你們出黑暗入奇妙光明者的美德。<br><a href='/CUNP/43/17/22'>約 17:22</a> 你所賜給我的榮耀，我已賜給他們，使他們合而為一，像我們合而為一。<p><a href='/CUNP/49/2/6'>弗 2:6</a> 他又叫我們與基督耶穌一同復活，一同坐在天上，<br><a href='/CUNP/46/6/11'>林前 6:11</a> 你們中間也有人從前是這樣；但如今你們奉主耶穌基督的名，並藉著我們神的靈，已經洗淨，成聖，稱義了。"
  },
  {
    "pk": 3511525,
    "translation": "CUNP",
    "book": 45,
    "chapter": 8,
    "verse": 31,
    "text": "既是這樣，還有甚麼說的呢？神若幫助我們，誰能敵擋我們呢？",
    "comment": "<a href='/CUNP/4/14/9'>民 14:9</a> 但你們不可背叛耶和華，也不要怕那地的居民；因為他們是我們的食物，並且蔭庇他們的已經離開他們。有耶和華與我們同在，不要怕他們！」<p><a href='/CUNP/19/118/6'>詩 118:6</a> 有耶和華幫助我，我必不懼怕，人能把我怎麼樣呢？"
  },
  {
    "pk": 3511526,
    "translation": "CUNP",
    "book": 45,
    "chapter": 8,
    "verse": 32,
    "text": "神既不愛惜自己的兒子，為我們眾人捨了，豈不也把萬物和他一同白白地賜給我們嗎？",
    "comment": "<a href='/CUNP/45/4/25'>羅 4:25</a> 耶穌被交給人，是為我們的過犯；復活，是為叫我們稱義<small>〔或作「耶穌是為我們的過犯交付了，是為我們稱義復活了。」〕</small>。<br><a href='/CUNP/45/5/6'>羅 5:6</a>, <a href='/CUNP/45/5/10'>10</a> 因我們還軟弱的時候，基督就按所定的日期為罪人死。……因為我們作仇敵的時候，且藉著神兒子的死，得與神和好；既已和好，就更要因他的生得救了。"
  },
  {
    "pk": 3511527,
    "translation": "CUNP",
    "book": 45,
    "chapter": 8,
    "verse": 33,
    "text": "誰能控告神所揀選的人呢？有神稱他們為義了<sup>〔或作「是稱他們為義的神嗎？」〕</sup>。",
    "comment": "<a href='/CUNP/23/50/8-9'>賽 50:8-9</a> 稱我為義的與我相近；誰與我爭論，可以與我一同站立；誰與我作對，可以就近我來。主耶和華要幫助我；誰能定我有罪呢？他們都像衣服漸漸舊了，為蛀蟲所咬。<p><a href='/CUNP/66/12/10-11'>啟 12:10-11</a> 我聽見在天上有大聲音說：「我神的救恩、能力、國度，並他基督的權柄，現在都來到了！因為那在我們神面前晝夜控告我們弟兄的，已經被摔下去了。弟兄勝過牠，是因羔羊的血和自己所見證的道。他們雖至於死，也不愛惜性命。"
  },
  {
    "pk": 3511528,
    "translation": "CUNP",
    "book": 45,
    "chapter": 8,
    "verse": 34,
    "text": "誰能定他們的罪呢？有基督耶穌已經死了，而且從死裏復活，現今在神的右邊，也替我們祈求<sup>〔「有基督云云」或作「是已經死了，而且從死裏復活，現今在神的右邊，也替我們祈求的基督耶穌嗎？」〕</sup>。",
    "comment": "<a href='/CUNP/41/16/19'>可 16:19</a> 主耶穌和他們說完了話，後來被接到天上，坐在神的右邊。<p><a href='/CUNP/51/3/1'>西 3:1</a> 所以，你們若真與基督一同復活，就當求在上面的事；那裏有基督坐在神的右邊。<p><a href='/CUNP/58/1/3'>來 1:3</a> 他是神榮耀所發的光輝，是神本體的真像，常用他權能的命令托住萬有。他洗淨了人的罪，就坐在高天至大者的右邊。<p><a href='/CUNP/58/8/1'>8:1</a> 我們所講的事，其中第一要緊的，就是我們有這樣的大祭司，已經坐在天上至大者寶座的右邊，<p><a href='/CUNP/58/12/1'>12:1</a> 我們既有這許多的見證人，如同雲彩圍著我們，就當放下各樣的重擔，脫去容易纏累我們的罪，存心忍耐，奔那擺在我們前頭的路程，<p><a href='/CUNP/60/3/22'>彼前 3:22</a> 耶穌已經進入天堂，在神的右邊；眾天使和有權柄的，並有能力的，都服從了他。<br><a href='/CUNP/58/7/25'>來 7:25</a> 凡靠著他進到神面前的人，他都能拯救到底；因為他是長遠活著，替他們祈求。<p><a href='/CUNP/58/9/24'>9:24</a> 因為基督並不是進了人手所造的聖所（這不過是真聖所<small>〔這不過是真聖所的影像〕</small>的影像），乃是進了天堂，如今為我們顯在神面前；<p><a href='/CUNP/62/2/1'>約壹 2:1</a> 我小子們哪，我將這些話寫給你們，是要叫你們不犯罪。若有人犯罪，在父那裏我們有一位中保，就是那義者耶穌基督。<br><a href='/CUNP/18/34/29'>伯 34:29</a> 他使人安靜，誰能擾亂<small>〔或作「定罪」〕</small>呢？他掩面，誰能見他呢？無論待一國或一人都是如此──"
  },
  {
    "pk": 3511529,
    "translation": "CUNP",
    "book": 45,
    "chapter": 8,
    "verse": 35,
    "text": "誰能使我們與基督的愛隔絕呢？難道是患難嗎？是困苦嗎？是逼迫嗎？是飢餓嗎？是赤身露體嗎？是危險嗎？是刀劍嗎？"
  },
  {
    "pk": 3511530,
    "translation": "CUNP",
    "book": 45,
    "chapter": 8,
    "verse": 36,
    "text": "如<i>經上</i>所記：我們為你的緣故終日被殺；人看我們如將宰的羊。",
    "comment": "<a href='/CUNP/19/44/22'>詩 44:22</a> 我們為你的緣故終日被殺；人看我們如將宰的羊。<p><a href='/CUNP/46/15/30-31'>林前 15:30-31</a> 我們又因何時刻冒險呢？弟兄們，我在我主基督耶穌裏，指著你們所誇的口極力地說，我是天天<na>冒</na>死。<p><a href='/CUNP/47/4/11'>林後 4:11</a> 因為我們這活著的人是常為耶穌被交於死地，使耶穌的生在我們這必死的身上顯明出來。"
  },
  {
    "pk": 3511531,
    "translation": "CUNP",
    "book": 45,
    "chapter": 8,
    "verse": 37,
    "text": "然而，靠著愛我們的<i>主</i>，在這一切的事上已經得勝有餘了。",
    "comment": "<a href='/CUNP/46/15/57'>林前 15:57</a> 感謝神，使我們藉著我們的主耶穌基督得勝。<p><a href='/CUNP/47/2/14'>林後 2:14</a> 感謝神！常率領我們在基督裏誇勝，並藉著我們在各處顯揚那因認識基督而有的香氣。<p><a href='/CUNP/62/4/4'>約壹 4:4</a> 小子們哪，你們是屬神的，並且勝了他們；因為那在你們裏面的，比那在世界上的更大。<p><a href='/CUNP/62/5/4-5'>5:4-5</a> 因為凡從神生的，就勝過世界；使我們勝了世界的，就是我們的信心。勝過世界的是誰呢？不是那信耶穌是神兒子的嗎？<p><a href='/CUNP/66/12/11'>啟 12:11</a> 弟兄勝過牠，是因羔羊的血和自己所見證的道。他們雖至於死，也不愛惜性命。"
  },
  {
    "pk": 3511532,
    "translation": "CUNP",
    "book": 45,
    "chapter": 8,
    "verse": 38,
    "text": "因為我深信無論是死，是生，是天使，是掌權的，是有能的，是現在的事，是將來的事，",
    "comment": "<a href='/CUNP/49/1/21'>弗 1:21</a> 遠超過一切執政的、掌權的、有能的、主治的，和一切有名的；不但是今世的，連來世的也都超過了。<p><a href='/CUNP/49/6/12'>6:12</a> 因我們並不是與屬血氣的爭戰，乃是與那些執政的、掌權的、管轄這幽暗世界的，以及天空屬靈氣的惡魔爭戰<small>〔兩「爭戰」原文都作「摔跤」〕</small>。<p><a href='/CUNP/51/1/16'>西 1:16</a> 因為萬有都是靠他造的，無論是天上的，地上的；能看見的，不能看見的；或是有位的，主治的，執政的，掌權的；一概都是藉著他造的，又是為他造的。<p><a href='/CUNP/51/2/15'>2:15</a> 既將一切執政的、掌權的擄來，明顯給眾人看，就仗著十字架誇勝。<p><a href='/CUNP/60/3/22'>彼前 3:22</a> 耶穌已經進入天堂，在神的右邊；眾天使和有權柄的，並有能力的，都服從了他。"
  },
  {
    "pk": 3511533,
    "translation": "CUNP",
    "book": 45,
    "chapter": 8,
    "verse": 39,
    "text": "是高處的，是低處的，是別的受造之物，都不能叫我們與神的愛隔絕；這愛是在我們的主基督耶穌裏的。"
  }
]
